setup.py
mvs1package/SumSineSeries.py
mvs1package/__init__.py
mvs1package/tests.py
mvs1package.egg-info/PKG-INFO
mvs1package.egg-info/SOURCES.txt
mvs1package.egg-info/dependency_links.txt
mvs1package.egg-info/not-zip-safe
mvs1package.egg-info/top_level.txt