Metadata-Version: 1.0
Name: mvs1package
Version: 0.10
Summary: Sum of Sine Series
Home-page: UNKNOWN
Author: UNKNOWN
Author-email: UNKNOWN
License: UNKNOWN
Platform: UNKNOWN
